metafox_shared/__init__.py
metafox_shared/config.py
metafox_shared/utilis.py
metafox_shared/constants/api_constants.py
metafox_shared/constants/default_value_constants.py
metafox_shared/constants/string_constants.py
metafox_shared/constants/worker_constants.py
metafox_shared/dal/idatastore.py
metafox_shared/dal/mongo/mongo_client.py
metafox_shared/dal/redis/redis_client.py
metafox_shared/exceptions/db.py
metafox_shared-0.1.6.dist-info/licenses/LICENCE
metafox_shared-0.1.6.dist-info/METADATA
metafox_shared-0.1.6.dist-info/WHEEL
metafox_shared-0.1.6.dist-info/top_level.txt
metafox_shared-0.1.6.dist-info/RECORD
