Metadata-Version: 2.4
Name: metafox-shared
Version: 0.1.6
Summary: Shared configuration and utilities for MetaFOX project
Author-email: Radovan Draskovic <radovandk@gmail.com>
License: Apache-2.0
Project-URL: Homepage, https://metafox.readthedocs.io/en/latest/
Project-URL: Repository, https://github.com/Drashko73/metafox-shared
Requires-Python: >=3.10
License-File: LICENCE
Requires-Dist: PyYAML>=6.0.2
Requires-Dist: python-dotenv>=1.0.1
Requires-Dist: redis>=5.2.1
Requires-Dist: pymongo>=4.10.1
Dynamic: license-file
